.gitignore
LICENSE
README.txt
VEfile
lola.py
setup.py
test_lola.py
tox.ini
lola.egg-info/PKG-INFO
lola.egg-info/SOURCES.txt
lola.egg-info/dependency_links.txt
lola.egg-info/top_level.txt
lola.egg-info/zip-safe
test_scripts/env.py
test_scripts/exception.py
test_scripts/fail.py
test_scripts/output.py
test_scripts/pwd.py
test_scripts/success.py