Metadata-Version: 1.0
Name: lola
Version: 0.1.3
Summary: Lola runs small Python scripts quickly
Home-page: http://github.com/mgood/lola/
Author: Matt Good
Author-email: matt@matt-good.net
License: BSD
Platform: any
